{
  "id": "m28c-iv-c-4",
  "canonicalCitation": "M28C.IV.C.4",
  "title": "Rehabilitation Plans to Employability",
  "authorityLevel": "va-policy",
  "sourceType": "m28c",
  "sourceUrl": "https://www.knowva.ebenefits.va.gov/system/templates/selfservice/va_ssnew/help/customer/locale/en-US/portal/554400000001018/content/554400000156328/M28CIVC4-Rehabilitation-Plans-to-Employability",
  "officialStatus": "va-public",
  "lastChecked": "2026-05-26",
  "sourceUpdated": "2024-08-14",
  "status": "full-text-loaded",
  "fullTextStatus": "official-verbatim",
  "rawHtmlSha256": "7310639d4cbb6ee36962d69b0c8c0c5e275f0fa28eb947c2b4e25ac1c3a03988",
  "fullTextSha256": "7310639d4cbb6ee36962d69b0c8c0c5e275f0fa28eb947c2b4e25ac1c3a03988",
  "articleId": "554400000156328",
  "retrievedAt": "2026-05-26T04:25:10.478Z",
  "headingCount": 2,
  "tableCount": 0,
  "attachmentCount": 0,
  "noTruncation": {
    "passed": true
  },
  "fullText": "Chapter 4\nRehabilitation to Employability Plans\n4.01  Overview\n4.02  Rehabilitation to Employability Plans\na.  Employment Through Long-Term Services\nb.  Rapid Access to Employment Services\nc.  Re-employment\nd.  Individualized Written Rehabilitation Plan with a Deferred Vocational Goal\n4.03  Rehabilitation Services Provided in a Rehabilitation to Employability Plan\na.  Academic Coursework\nb.  Short-term Training or Certificate\nc.  Vocational Training Services\nd.  Independent Living Services\ne.  Employment Services\nf.  Subsistence Allowance\ng.  Case Management Assistance\nh.  Revolving Fund Loan\ni.  Counseling Services\nj.  Dental, Medical, and Mental Health Services\nk.  Payment for Licenses, Certifications, and Fees\nl.  Payment for Tuition, Books, and Supplies\n4.04  Reemployment Rights Information\n4.05  Development of a Rehabilitation to Employability Plan\na.  Individualized Written Rehabilitation Plan\nb.  Elements of the Plan\n4.06  Rehabilitation Plan Activities and Orientation Process\na.  VA Form 28-1902n, Counseling Record - Narrative Report\nb.  Guidelines for Planned Services\n4.01  Overview\n(Change Date August 15, 2013)\n\nUnder the provisions of title 38 of the Code of Federal Regulations (CFR) 21.70, the purpose of a claimant’s vocational rehabilitation program for employment includes the following:\n\nTo evaluate and improve the claimant’s ability to achieve an employment goal\nTo provide services needed to qualify the claimant for employment and become employable\nTo enable the claimant to obtain and maintain suitable employment\n\nAn effective plan leading to suitable employment begins during the comprehensive evaluation, which includes vocational assessments and exploration activities. These activities are necessary in identifying the claimant’s suitable vocational goal and a plan of services that will enable him or her to overcome employment barriers and achieve his or her employment goal. \n\nDuring the evaluation and planning phase, the Vocational Rehabilitation Counselor (VRC) must determine feasibility of the claimant to participate in a plan of services. \n\nThe VRC must develop the rehabilitation plan with the claimant and/or appointed guardian using the information gathered during his or her initial evaluation. The VRC must determine necessary rehabilitation services by conducting an analysis of the following factors:\n\nFunctional capacity and/or limitations\nEducation and/or training needs\nBasic independent living needs\nJob accommodations\nOther needs relevant to achievement of employment goal\n\nThis chapter provides the guidelines for developing a specific plan of services for rehabilitation to employability plans to assist a claimant in preparing for, obtaining, and maintaining suitable employment.\n\n4.02  Rehabilitation to Employability Plans\n\nThe tracks or services to employment are defined as follows:\n\na.  Employment Through Long-Term Services\n(Change Date August 15, 2013)             \n\nA plan for employment through long-term services provides a claimant an extended period of training and rehabilitation services to ensure that the claimant acquires the skills necessary to obtain and maintain suitable employment. \n\nThis track is provided to a claimant who may need extensive training or education and necessary rehabilitation services to overcome his or her impairment of employability. Services may include, but are not limited to, remedial or refresher courses; specialized training; post-secondary education; on-the-job training (OJT); non-paid work experience (NPWE); apprenticeships; and other necessary rehabilitation services. \n\nb.  Rapid Access to Employment Services\n(Change Date August 15, 2013)             \n\nA plan for rapid access to employment services provides a claimant services to enhance already acquired skills necessary for him or her to obtain and maintain employment without delay. \n\nThis plan of services is provided to claimants who express a desire to obtain employment as soon as possible and may already possess the necessary skills to qualify for competitive employment in a suitable career. Services to improve the claimant's rehabilitation potential may include short-term or refresher training, such as interview skills training; job-seeking techniques; resume development; assistance with translating military work experience into civilian work experience; and other necessary rehabilitation services. \n\nc.  Re-employment\n(Change Date August 15, 2013)\n\nA plan for reemployment services provides a claimant with necessary skills to return to the occupation he or she had held prior to entering active military service. This track is provided to a claimant who may need some short-term or refresher training and rehabilitation services to enhance his or her competency to return to his or her previous employment.\n\nIf the previous employment is no longer suitable, the claimant must be evaluated to determine if an alternative suitable vocational goal with the same employer is an option. If the claimant can no longer return to his or her previous employer, the VRC should explore the other tracks for employment. \n\nd.  Individualized Written Rehabilitation Plan with a Deferred Vocational Goal\n(Change Date March 12, 2021)\n\nThe development of an Individualized Written Rehabilitation Plan (IWRP) with a Deferred Vocational Goal provides a plan of services that will allow provision of training to a claimant, for whom a suitable vocational goal cannot be readily identified, while the claimant is completing the vocational exploration and planning process to identify a suitable vocational goal.\n\nBasically, this process allows a claimant’s case to “move” from Evaluation and Planning (EP) status to Rehabilitation To the point of Employability (RTE) status without having an identified vocational goal. Vocational exploration and planning activities are conducted in RTE status while the claimant is simultaneously attending training.\n\n1.   Criteria for an IWRP with a Deferred Vocational Goal\n\n(Change Date March 12, 2021)\n\nThe following conditions must be met prior to the execution of an IWRP with a Deferred Vocational Goal:\n\na. The claimant’s achievement of a vocational goal has been determined currently and reasonably feasible.\n\nb. The claimant’s vocational goal cannot be readily identified at the time the plan is developed.\n\nc. The IWRP must include vocational exploration and planning activities.\n\nd. The IWRP must include a training objective for needed remedial and/or general education course(s) only.\n\ne. The training must begin within three months from the date the IWRP with a Deferred Vocational Goal was signed by the VRC and the claimant, for any case in which entitlement was determined under the provision of 38 U.S.C. 3102.\n\nf. The training must begin within six months from the date the IWRP with a Deferred Vocational Goal was signed by the VRC and the claimant, for any case in which entitlement was determined under the provision of the National Defense Authorization Act for FY 2008.\n\ng. The maximum training period is one standard term or two non-standard terms.\n\nh. The plan must be redeveloped with a suitable vocational goal and appropriate objectives within nine months from the date entitlement was determined.\n\n2.   Components of the Plan\n(Change Date March 12, 2021)\n\nAn IWRP with a Deferred Vocational Goal must include, but is not limited to, the following conditions:\n\na. The program goal of the plan is “To determine a suitable occupational goal”. DOT 999, Deferred, must be used since a vocational goal has not been identified.\n\nb. The IWRP must include a training objective, which is limited to needed remedial training or general education courses only.\n\nc. Vocational objectives, which outline evaluations or sources of information that will assist in determining a suitable vocational goal, such as a background check, medical evaluations, or labor market research.\n\nd. Health and medical services objective that addresses appropriate medical, psychological, counseling, and health-related services.\n\ne. Case management level, which specifies Level 3 for the required monthly face-to-face meeting.\n\n3. Documentation for the Rationale of the Plan\n(Change Date March 12, 2021)\n\nThe VRC must document the reason(s) for developing an IWRP with a Deferred Vocational Goal for each claimant. The documentation must explain the circumstance(s) that justify deferral of the claimant’s vocational goal. Justification must be documented on VAF 28-1902n, Counseling Record and Narrative Report.\n\n4. Exceptions\n\n(Change Date March 12, 2021)\n\nAn IWRP with a Deferred Vocational Goal must not be used for any of the following intended services:\n\na. Extended evaluation\n\nb. Independent living\n\nc. Self-employment\n\n5. Retroactive Induction and Retroactive Reimbursement\n\n(Change Date March 12, 2021)\n\nA request for retroactive induction or reimbursement cannot be approved with the development of an IWRP with a Deferred Vocational Goal. Retroactive induction or reimbursement can only be approved after all the following conditions are met:\n\na. A vocational goal has been identified for the claimant.\n\nb. A DOT code other than 999 has been identified.\n\nc. The VRC has determined that prior training will contribute to the completion of the claimant’s identified vocational goal.\n\nRefer to M28C.V.B.6 for additional information about retroactive induction or retroactive reimbursement.\n\n6. Identified Vocational Goal\n\n(Change Date March 12, 2021)\n\nOnce a vocational goal is identified, the IWRP must be redeveloped with the suitable vocational goal. Interruption of the case is not required when redeveloping the IWRP unless an extended period is necessary to redevelop the plan.\n\n7. Case Closure\n\n(Change Date March 12, 2021)\n\na. If a claimant does not follow through with planned services, or elects to discontinue participation in the program, the case must be placed in Interrupted (INT) status using reason code (RC) 16. The claimant must be provided with   the required due process. Subsequent steps must be taken to discontinue the case. \n\nb. Rehabilitation or MRG closure is not applicable for discontinuance of a case under an IWRP with a Deferred Vocational Goal since a suitable vocational goal has not been identified.\n\n8.  Required Plan Tracking\n(Change Date March 12, 2021)\nEach VR&E Officer must monitor the progress of claimants, who are participating in an IWRP with a Deferred Vocational Goal, to ensure that the plan does not exceed the specified time limits, and that a suitable vocational goal is eventually identified.\nThese cases can be identified by accessing the VBA Reports at the Office of Performance Analysis and Integrity website at selecting the Dashboard report titled \"Occupation\", and filtering by DOT code 999. \n \n4.03  Rehabilitation Services Provided in a Rehabilitation to Employability Plan\n(Change Date August 15, 2013)\n\nThe provision of rehabilitation services is governed by 38 U.S.C. 3104 to assist the claimant to reach his or her vocational goal.  The services outlined in the rehabilitation plan are developed according to the individual needs of the claimant. The services may include, but are not limited to the following:\n\na.  Academic Coursework\n(Change Date August 15, 2013)\n\nAcademic coursework is a key component of most employment through long-term services plans. It is provided to assist the claimant in obtaining the skills and education necessary to obtain and maintain suitable employment.\n\nb.  Short-term Training or Certificate\n(Change Date August 15, 2013)  \n\nA short-term training is provided to enhance the claimant’s employment skills and/or obtain professional certification if the VRC determines that these skills/certifications are necessary for the claimant to obtain and maintain suitable employment. This short-term training may be provided in a re-employment plan or rapid access to employment plan.\n\nc.  Vocational Training Services\n(Change Date August 15, 2013)\n\nThese services include on-job training (OJT), apprenticeship, non-paid work experience (NPWE), farm cooperative, independent study, and home study. These different types of services may be provided to a claimant who needs hands-on or practical demonstration of work tasks to meet the requirements for employment. Refer to for more information on vocational training services.  Refer to M28C.V.A.1 for more information on vocational training services.\n\nd.  Independent Living Services\n(Change Date August 15, 2013)\n\nWhen results from the preliminary independent living assessment during the initial evaluation identified that the claimant has independent living needs, the VRC must ensure that corresponding rehabilitation services are outlined as part of the intermediate objectives of the claimant’s plan.\n\ne.  Employment Services\n(Change Date August 15, 2013)\n\nIn accordance with 38 CFR 21.88, an Individualized Employment Assistance Plan (IEAP) will be developed as part of an Individualized Written Rehabilitation Plan (IWRP), or an IEAP will be developed when a claimant is eligible for employment assistance under the provisions of 38 CFR 21.47.\n\nAn IWRP/IEAP may be developed for a rehabilitation plan with a program goal of employment. However, when a claimant has been declared job ready, the IWRP/IEAP may be updated to reflect all identified employment services and period of services, as necessary. Conversely, an IEAP may be developed within 60 days prior to the claimant's completion of his or her training program.       \n\nf.  Subsistence Allowance\n(Change Date August 15, 2013)\n\nA subsistence allowance is monetary assistance provided to a claimant participating in a training program. The subsistence allowance is paid in accordance with 38 CFR 21.260. Refer to M28C.V.B.7 for procedural guidance on payment of subsistence allowance.\n\ng.  Case Management Assistance\n(Change Date August 15, 2013)\n\nThe VRC must provide the claimant with continuing assistance while he or she is participating in a rehabilitation plan. The VRC must ensure that regular contact is maintained with the claimant to ensure that claimant progresses satisfactorily toward his or her employment goal. Refer to the M28C.IV.C.2 for required levels of case management and M28C.V.A.2 for case management assistance.  \n\nh.  Revolving Fund Loan\n(Change Date August 15, 2013)\n\nA revolving fund loan (RFL) provides advances to a claimant who may be unable to begin, continue, or reenter his or training program. A VRC may approve a claimant’s request for an RFL in accordance with 38 CFR 21.274(d). Refer to M28C.V.B.8 for procedural guidance on advances from the revolving fund.\n\ni.  Counseling Services\n(Change Date August 15, 2013)\n\nIn accordance with 38 U.S.C. 3107, all rehabilitation plans must include counseling. The VRC must ensure that counseling services are provided as one of the objectives of the claimant’s rehabilitation plan. These services can assist the claimant in making informed decisions in using his or her VA benefits, and resolving adjustment issues that may affect his or her ability to achieve his or her chosen vocational goal. The types of counseling services may include, but are not limited to psychological, vocational, personal adjustment, employment, or educational.\n\nj.  Dental, Medical, and Mental Health Services\n(Change Date August 15, 2013)  \n\nA claimant must be provided with medical treatment, care, and services that the VRC determines necessary to complete his or her rehabilitation program. The VRC must ensure that these services are included as an objective in the claimant’s rehabilitation plan. \n\nThe VRC makes the referral for dental, medical, and mental health services to the VA Medical Center (VAMC) as needed by the claimant to ensure his or her health condition is optimally maintained. If VAMC is unable to provide those services, service providers outside VA may provide those services through the VAMC fee basis.  \n\nRefer to M28C.V.A.4  for additional information on medical and other related services.\n\nk.  Payment for Licenses, Certifications, and Fees\n(Change Date August 15, 2013)\n\nThe case manager may authorize payment for a license, certificate, or fee when a claimant’s employment goal requires the occupational or professional qualifications. Payment may include the cost of examinations required to obtain the license, permit, or certificate. The claimant must meet all prerequisites for taking the examination, such as successful completion of training, prior to authorizing payment as outlined in 38 CFR 21.254(a).\n\nl.  Payment for Tuition, Books, and Supplies\n(Change Date August 15, 2013)\n\nA claimant’s attendance in a training facility is paid by VA. This also includes payment for books, tools, and other supplies and equipment that are determined necessary for the claimant’s vocational rehabilitation program as outlined in 38 CFR 21.210.  Refer to M28C.V.A.3 and M28C.V.B.2 for procedural guidance for authorizing payments for tuition, books, and supplies.\n\n4.04  Reemployment Rights Information\n(Change Date August 15, 2013)\n\nServices provided in the re-employment plan are focused on returning the claimant to the position he or she held prior to active duty. The VRC must complete an occupational analysis to ensure that the claimant’s previous employment is suitable, with or without accommodations, and the claimant has the functional capacity to return to his or her former position. \n\nThe VRC must have sufficient knowledge of the Uniformed Services Employment and Reemployment Rights Act (USERRA) to assist a claimant to return to his or her previous occupation. Refer to USERRA for detailed information and File a Claim for information on applying for USERRA.\n\nUSERRA protects civilian job rights and benefits for Veterans and members of the active and Reserve components of the U.S. armed forces. USERRA states that returning Service members must be promptly re-employed in the same position that they would have attained had they not been absent for military service, with the same seniority, status and pay, as well as other rights and benefits determined by seniority.\n\nUSERRA establishes the cumulative length of time that an individual may be absent from work for military duty and retain reemployment rights to five years (the previous law provided four years of active duty, plus an additional year if it was for the convenience of the Government). There are important exceptions to the five-year limit, including initial enlistments lasting more than five years, periodic National Guard and Reserve training duty, and involuntary active duty extensions and recalls, especially during a time of national emergency. USERRA clearly establishes that reemployment protection does not depend on the timing, frequency, duration, or nature of an individual's service if the basic eligibility criteria are met.\n\nUSERRA provides protection for claimants with disabilities, requiring employers to make reasonable efforts to accommodate the disability. Service members convalescing from injuries received during service or training may have up to two years from the date of completion of service to return to their jobs or apply for reemployment.\n\nThe period for an individual to apply for re-employment or report back to work after military service is based on time spent on military duty.\n\nFor service of less than 31 days, the Service member must return at the beginning of the next regularly scheduled work period on the first full day after release from service, considering safe travel home plus an eight-hour rest period. \nFor service of more than 30 days but less than 181 days, the Service member must submit an application for reemployment within 14 days of release from service.\nFor service of more than 180 days, an application for reemployment must be submitted within 90 days of release from service.\n\nUSERRA also requires that Service members provide advance written or verbal notice to their employers for all military duty unless giving notice is impossible, unreasonable, or precluded by military necessity. An employee should provide notice as far in advance as is reasonable under the circumstances. Additionally, Service members are able (but are not required) to use accrued vacation or annual leave while performing military duty.\n\nIf a Veteran or Service member believes his or her re-employment rights are being violated, the VRC must coordinate services by referring him or her to the Department of Labor (DOL) Veterans' Employment and Training Service (VETS), or the Department of Defense Employer Support of the Guard and Reserve. \n\n4.05  Development of a Rehabilitation to Employability Plan\n(Change Date August 15, 2013)\n\nA rehabilitation to employability plan will be developed for any claimant whose achievement of a vocational goal is reasonably currently feasible and whose rehabilitation goal is to obtain and maintain employment. \n\nThis plan is designed for a claimant who will pursue re-employment, rapid access to employment, or employment through long-term services.\n\nNote:  A self-employment plan is not included in this chapter since the requirements and services required for self-employment is distinct from these plans. Refer to M28C.IV.C.5 for procedural guidelines for developing a self-employment plan.\n\na.  Individualized Written Rehabilitation Plan\n(Change Date July 14, 2022)\n\nWhen a claimant’s vocational goal has been identified, the VRC must determine the claimant’s rehabilitation needs and identify the corresponding services that will assist the claimant to overcome his or her impairment to employability.\n\nAn individualized written rehabilitation plan (IWRP) must be developed when the claimant is pursuing re-employment, rapid access to employment, employment through long-term services, or when developing an IWRP with a deferred vocational  goal. The IWRP must be documented on VA Form 28-10214, Rehabilitation Plan.\n\nb.  Elements of the Plan\n(Change Date August 15, 2013)\n\nAn IWRP must outline one vocational goal and intermediate objectives or services to be provided to the claimant.\n\nThe following are required considerations when developing an IWRP:\n\n1.  Vocational Goal\n(Change Date August 15, 2013)\n\nAn IWRP must state a long-range employment goal, which clearly identifies the chosen occupational goal that the claimant must achieve during the period of rehabilitation services.\n\n2.  Intermediate Objectives\n(Change Date August 15, 2013)\n\nThe IWRP must specify the intermediate objectives that outline specific services necessary for the claimant to obtain and maintain suitable employment. These services are identified but are not limited in section of this chapter.\n\nAn intermediate objective provides specific components of the services that will assist the claimant to achieve his or her employment goal.\n\nPer 38 CFR 21.84(b)(2), an intermediate objective must have the following components:\n\na. The objective must be related to the achievement of the occupational or employment goal and must be observable and measurable. Example: The claimant will complete Associate of Arts in Computer Science.\n\nb. The services for the objective to be provided are clearly specified. Refer to section 4.03 of this chapter.\n\nc. Counseling services must be provided to all claimants with SEH.\n\nd. The services to be provided must have a begin date and an end date.\n\ne. The name, address, contact person, and information of the service provider must be specified.\n\nf. The claimant's progress must be determined by identifying the following activities in the plan:\n\nEvaluation Criteria - must specify the basis or measure for the evaluation. Example: Compliance with the training facility’s policies on attendance, progress, and conduct as published in the school catalog.\nEvaluation Procedure - must specify the method that will measure the claimant’s progress while participating in a specific service. Example: Training progress or grades.\nEvaluation Schedule - must specify the frequency of evaluation of the specific service that will be provided to the claimant. \n3.  Other Considerations for Plan Development\n(Change Date August 15, 2013) \n\nIn addition to the services specified in section 4.03 of this chapter, the VRC must ensure that the requisites outlined below are evaluated, and if considered, actions must be taken and outlined in the IWRP as necessary.\n\na. Election of Benefits (M28C.IV.C.2)\n\nb. Retroactive Induction or Retroactive Reimbursement (M28C.V.B.6)\n\nc. Approval of Program Costs (M28C.V.B.1)\n\nd. Reduced Work Tolerance (M28C.IV.C.2)\n\ne. Approval for Chapter 31 only Programs of Training or Courses (M28C.IV.A.1)\n\nf. Extension of Entitlement (M28C.IV.C.1)\n\n4.  Required Signatures\n(Change Date August 15, 2013)\n\nAn IWRP is an agreement between the VA and the claimant; therefore, the VRC and the claimant must sign the rehabilitation plan and any amendments of plans. \n\n4.06  Rehabilitation Plan Activities and Guidelines\na.  VA Form 28-1902n, Counseling Record - Narrative Report\n(Change Date January 10, 2020)\n\nThe VRC must ensure that all planning activities are completed and documented on VAF 28-1902n prior to the implementation of the plan, as outlined in M28C.IV.B.2.04.   \n\nb.  Guidelines for Planned Services\n(Change Date May 6, 2022)\n\nOnce the rehabilitation plan is signed by the VRC and the claimant, the VRC must provide the claimant with a VR&E orientation to ensure that the claimant understands the VRC’s and his or her roles and requirements during the rehabilitation program. The claimant must be provided VAF 28-0957, Vocational Rehabilitation Guidelines and Debt Prevention, which informs the claimant of specific requirements when completing his or her vocational training and how to avoid creating a debt with VA. \n\nDuring the orientation, the VRC must provide the claimant with concise and accurate information to ensure successful completion of his or her rehabilitation program. The orientation must include, but is not limited to, the following;\n\nUnderstanding payment of subsistence allowance\nMaintaining satisfactory conduct and cooperation\nReporting changes in contact information, number of dependents and rate of participation, and changes in circumstances\nObtaining required books, and supplies\nRequesting medical treatment and other services\nMaintaining regular contact with the VRC\n\nAfter the orientation, the VRC and the claimant must sign the IWRP. The claimant must sign the VAF 28-0957. The VRC must place a copy of the two forms in the claimant’s VR&E record.\n\n \n\n \n\nBack to Top of Page\n\nWMK2\n\n\t\n.",
  "plainEnglish": "Procedural instructions on how you and your counselor construct your written plan (IWRP) once entitled.",
  "veteranUse": "Ensures that all services, tuition, fees, and technology are formally written into your plan so they cannot be unilaterally revoked later.",
  "topics": [
    "iwrp",
    "rehab-plan",
    "goals"
  ],
  "relatedAuthorities": [
    "38-usc-3107",
    "38-cfr-21-84",
    "38-cfr-21-94"
  ],
  "publicLawRefs": [],
  "federalRegisterRefs": [],
  "amendmentNotes": [],
  "hash": "7310639d4cbb6ee36962d69b0c8c0c5e275f0fa28eb947c2b4e25ac1c3a03988",
  "previousHash": "c4ca9dfead50a0a7645f9f928b35c134c9afe4460346cc711c19db86f4aee282",
  "snapshotDate": "2026-05-25",
  "sourceLastChecked": "2026-05-25",
  "changedSinceLastSnapshot": false
}