{
  "id": "38-cfr-21-218",
  "canonicalCitation": "38 C.F.R. § 21.218",
  "title": "Methods of furnishing supplies.",
  "authorityLevel": "binding-regulation",
  "sourceType": "cfr",
  "sourceUrl": "https://www.ecfr.gov/api/renderer/v1/content/enhanced/2026-05-21/title-38?part=21&subpart=A",
  "officialStatus": "current-unofficial",
  "lastChecked": "2026-05-25",
  "sourceUpdated": "2026-05-21",
  "effectiveDate": null,
  "status": "current",
  "fullText": "(a) Supplies furnished by the school or facility.  VA will make arrangements for the school or other facility furnishing a veteran training, rehabilitation assistance, or employment under Chapter 31 to provide supplies to the extent practicable. This method is the one most likely to assure that supplies are available and can be secured expeditiously. A facility may be considered to be furnishing supplies when the facility itself is the supplier, or the facility has designated a supplier. Prior authorization of supplies by the case manager is required, except for standard sets of books, tools, or supplies which the facility requires all trainees or employees to have.\n\n(b) Issuance of supplies not furnished by the facility.  VA will issue authorized supplies directly to the veteran, if the supplies are not furnished by the facility providing training, rehabilitation services, or employment.\n\n(Authority: 38 U.S.C. 3104(a))\n\nCross Reference:\n\nSee 48 CFR part 831. Contract cost principles and procedures.",
  "plainEnglish": "Explanatory guidance for 38 C.F.R. § 21.218.",
  "veteranUse": "Cite this regulation in your claim to establish counselor duty under § 21.218.",
  "topics": [
    "chapter-31",
    "regulation"
  ],
  "relatedAuthorities": [],
  "publicLawRefs": [],
  "federalRegisterRefs": [],
  "amendmentNotes": [],
  "hash": "57a09e96858c01ee245058d7d77a3f589e40de661839d2c5221d37ae4820c59c"
}