{
  "id": "3113",
  "citation": "38 U.S.C. § 3113",
  "title": "Vocational rehabilitation for hospitalized members of the Armed Forces and veterans",
  "text": "(a) Services and assistance may be provided under this chapter to a person described in subparagraphs (A)(ii) and (B) of section 3102(1) of this title who is hospitalized pending discharge from active military, naval, air, or space service. In such cases, no subsistence allowance shall be paid.\n\n(b) Services and assistance may be provided under this chapter to a veteran who is receiving care in a Department of Veterans Affairs hospital, nursing home, or domiciliary facility or in any other hospital or medical facility.",
  "sourceCredit": "(Added \n\nPub. L. 96–466, title I, §101(a), Oct. 17, 1980, 94 Stat. 2181\n, §1513; amended \n\nPub. L. 101–237, title IV, §423(b)(1)(B), Dec. 18, 1989, 103 Stat. 2092\n; renumbered §3113 and amended \n\nPub. L. 102–83, §5(a), (c)(1), Aug. 6, 1991, 105 Stat. 406\n; \n\nPub. L. 103–446, title XII, §1201(d)(10), Nov. 2, 1994, 108 Stat. 4684\n; \n\nPub. L. 116–283, div. A, title IX, §926(a)(43), Jan. 1, 2021, 134 Stat. 3830\n.)",
  "notes": "Editorial Notes\n\nPrior Provisions\n\nPrior section 3113 was renumbered section 5313 of this title.\n\nProvisions similar to those comprising subsec. (a) of this section were contained in former section 1510 of this title prior to the general revision of this chapter by \n\nPub. L. 96–466.\n\nAmendments\n\n2021-Subsec. (a). \n\nPub. L. 116–283 substituted \"air, or space service\" for \"or air service\".\n\n1994-Subsec. (a). \n\nPub. L. 103–446 substituted \"subparagraphs (A)(ii) and (B) of section 3102(1)\" for \"section 3102(1)(B) and (2)\".\n\n1991-\n\nPub. L. 102–83, §5(a), renumbered section 1513 of this title as this section.\n\nSubsec. (a). \n\nPub. L. 102–83, §5(c)(1), substituted \"3102(1)(B)\" for \"1502(1)(B)\".\n\n1989-Subsec. (b). \n\nPub. L. 101–237 substituted \"Department of Veterans Affairs\" for \"Veterans' Administration\".\n\nStatutory Notes and Related Subsidiaries\n\nEffective Date\n\nSection effective Apr. 1, 1981, see section 802(a)(1) of \n\nPub. L. 96–466, set out as a note under section 3100 of this title.",
  "level": "binding_law",
  "lastChecked": "2026-05-25"
}